shareplum/ListDict.py
shareplum/__init__.py
shareplum/errors.py
shareplum/folder.py
shareplum/list.py
shareplum/list_dict.py
shareplum/office365.py
shareplum/request_helper.py
shareplum/shareplum.py
shareplum/site.py
shareplum/soap.py
shareplum/version.py
SharePlum-0.5.1.dist-info/LICENSE.txt
SharePlum-0.5.1.dist-info/METADATA
SharePlum-0.5.1.dist-info/WHEEL
SharePlum-0.5.1.dist-info/top_level.txt
SharePlum-0.5.1.dist-info/RECORD
