Metadata-Version: 1.1
Name: SharePlum
Version: 0.5.1
Summary: Python SharePoint Library
Home-page: https://github.com/jasonrollins/shareplum
Author: Jason Rollins
Author-email: jason.c.rollins@gmail.com
License: MIT
Keywords: SharePoint
Platform: UNKNOWN
Classifier: Development Status :: 4 - Beta
Classifier: License :: OSI Approved :: MIT License
Classifier: Programming Language :: Python
Classifier: Programming Language :: Python :: 3.6
Classifier: Programming Language :: Python :: 3.7
Classifier: Programming Language :: Python :: 3.8
Classifier: Intended Audience :: Developers
Classifier: Intended Audience :: Information Technology
Classifier: Intended Audience :: System Administrators
Classifier: Operating System :: OS Independent
Classifier: Topic :: Internet :: WWW/HTTP
Classifier: Topic :: Office/Business
